cake.py
disco.py
heart.py
main.py
virus.py
turtle_cli_graphics-0.1.2.data/data/dooron.wav
turtle_cli_graphics-0.1.2.data/data/rabba.wav
turtle_cli_graphics-0.1.2.dist-info/licenses/LICENSE
turtle_cli_graphics-0.1.2.dist-info/METADATA
turtle_cli_graphics-0.1.2.dist-info/WHEEL
turtle_cli_graphics-0.1.2.dist-info/entry_points.txt
turtle_cli_graphics-0.1.2.dist-info/top_level.txt
turtle_cli_graphics-0.1.2.dist-info/RECORD
