Metadata-Version: 2.4
Name: turtle-cli-graphics
Version: 0.1.2
Summary: A CLI tool for drawing graphics with turtle and playing sounds
Home-page: https://github.com/turtle-cli/turtle-cli-graphics
Author: Turtle CLI
Author-email: Turtle CLI <turtle@example.com>
License: MIT
Project-URL: Homepage, https://github.com/turtle-cli/turtle-cli-graphics
Classifier: Programming Language :: Python :: 3
Classifier: License :: OSI Approved :: MIT License
Classifier: Operating System :: OS Independent
Requires-Python: >=3.6
License-File: LICENSE
Requires-Dist: simpleaudio
Dynamic: author
Dynamic: home-page
Dynamic: license-file
Dynamic: requires-python
